src/__init__.py
src/cli.py
src/cmd.py
src/codeMsg.py
src/common.py
src/config.py
src/create.py
src/download.py
src/log.py
src/login.py
src/logout.py
src/project.py
src/pull.py
src/run.py
src/upload.py
fkit-0.0.30.dist-info/METADATA
fkit-0.0.30.dist-info/WHEEL
fkit-0.0.30.dist-info/entry_points.txt
fkit-0.0.30.dist-info/top_level.txt
fkit-0.0.30.dist-info/RECORD
